biogeme_optimization/__init__.py
biogeme_optimization/algebra.py
biogeme_optimization/bfgs.py
biogeme_optimization/biogeme_logging.py
biogeme_optimization/bounds.py
biogeme_optimization/diagnostics.py
biogeme_optimization/exceptions.py
biogeme_optimization/floating_point.py
biogeme_optimization/format.py
biogeme_optimization/function.py
biogeme_optimization/hybrid_function.py
biogeme_optimization/linesearch.py
biogeme_optimization/neighborhood.py
biogeme_optimization/pareto.py
biogeme_optimization/simple_bounds.py
biogeme_optimization/stochastic_function.py
biogeme_optimization/stochastic_simple_bounds.py
biogeme_optimization/trust_region.py
biogeme_optimization/version.py
biogeme_optimization/vns.py
biogeme_optimization-0.0.11.dist-info/METADATA
biogeme_optimization-0.0.11.dist-info/WHEEL
biogeme_optimization-0.0.11.dist-info/top_level.txt
biogeme_optimization-0.0.11.dist-info/RECORD
