Metadata-Version: 2.4
Name: biogeme-optimization
Version: 0.0.11
Summary: Various optimization algorithms for teaching and research
Author-email: Michel Bierlaire <michel.bierlaire@epfl.ch>
Project-URL: Code, https://github.com/michelbierlaire/optimization
Project-URL: homepage, http://biogeme.epfl.ch
Project-URL: download-url, https://pypi.org/project/bierlaire-optimization
Classifier: Intended Audience :: Education
Classifier: Intended Audience :: Science/Research
Classifier: Topic :: Scientific/Engineering
Classifier: Topic :: Scientific/Engineering :: Mathematics
Classifier: Natural Language :: English
Classifier: Operating System :: OS Independent
Classifier: Programming Language :: Cython
Classifier: Programming Language :: Python
Classifier: Programming Language :: Python :: 3
Classifier: Programming Language :: Python :: 3 :: Only
Requires-Dist: numpy<3,>=2.2.6
Requires-Dist: scipy<2,>=1.15.3
Requires-Dist: matplotlib<4,>=3.10.3
Requires-Dist: tomlkit<1,>=0.13.2
Provides-Extra: testing
Requires-Dist: pytest>=8.3.5; extra == "testing"
Requires-Dist: pytest-cov>=6.1.1; extra == "testing"
Requires-Dist: tox>=4.26.0; extra == "testing"
